DISCLAIMER
LICENSE
NOTICE
README.md
apache_liminal_test_spark-0.0.0.data/scripts/liminal
liminal/__init__.py
liminal/build/__init__.py
liminal/build/image_builder.py
liminal/build/liminal_apps_builder.py
liminal/build/python.py
liminal/build/__pycache__/__init__.cpython-37.pyc
liminal/build/__pycache__/image_builder.cpython-37.pyc
liminal/build/__pycache__/liminal_apps_builder.cpython-37.pyc
liminal/build/__pycache__/python.cpython-37.pyc
liminal/build/image/__init__.py
liminal/build/image/__pycache__/__init__.cpython-37.pyc
liminal/build/image/__pycache__/__init__.cpython-38.pyc
liminal/build/image/java/__pycache__/__init__.cpython-37.pyc
liminal/build/image/java/__pycache__/__init__.cpython-38.pyc
liminal/build/image/java/__pycache__/java.cpython-37.pyc
liminal/build/image/java/__pycache__/java.cpython-38.pyc
liminal/build/image/python/Dockerfile
liminal/build/image/python/__init__.py
liminal/build/image/python/python.py
liminal/build/image/python/__pycache__/__init__.cpython-37.pyc
liminal/build/image/python/__pycache__/__init__.cpython-38.pyc
liminal/build/image/python/__pycache__/python.cpython-37.pyc
liminal/build/image/python/__pycache__/python.cpython-38.pyc
liminal/build/image/python_server/__pycache__/__init__.cpython-37.pyc
liminal/build/image/python_server/__pycache__/__init__.cpython-38.pyc
liminal/build/image/python_server/__pycache__/liminal_python_server.cpython-37.pyc
liminal/build/image/python_server/__pycache__/liminal_python_server.cpython-38.pyc
liminal/build/image/python_server/__pycache__/python_server.cpython-37.pyc
liminal/build/image/spark/Dockerfile
liminal/build/image/spark/__init__.py
liminal/build/image/spark/spark.py
liminal/build/image/spark/__pycache__/__init__.cpython-37.pyc
liminal/build/image/spark/__pycache__/spark.cpython-37.pyc
liminal/build/service/__init__.py
liminal/build/service/service_image_builder.py
liminal/build/service/__pycache__/__init__.cpython-37.pyc
liminal/build/service/__pycache__/__init__.cpython-38.pyc
apache_liminal_test_spark-0.0.0.dist-info/LICENSE
apache_liminal_test_spark-0.0.0.dist-info/METADATA
apache_liminal_test_spark-0.0.0.dist-info/NOTICE
apache_liminal_test_spark-0.0.0.dist-info/WHEEL
apache_liminal_test_spark-0.0.0.dist-info/top_level.txt
apache_liminal_test_spark-0.0.0.dist-info/RECORD
