Metadata-Version: 2.1
Name: apache-liminal-test-spark
Version: 0.0.0
Summary: A package for authoring and deploying machine learning workflows
Home-page: https://github.com/apache/incubator-liminal
Author: dev@liminal.apache.org
Author-email: dev@liminal.apache.org
License: Apache License, Version 2.0
Platform: UNKNOWN
Classifier: Programming Language :: Python :: 3
Classifier: License :: OSI Approved :: Apache Software License
Classifier: Operating System :: OS Independent
Requires-Python: >=3.6
Requires-Dist: docker (==4.2.0)
Requires-Dist: apache-airflow (==1.10.12)
Requires-Dist: click (==7.1.1)
Requires-Dist: Flask (==1.1.1)
Requires-Dist: pyyaml (==5.3.1)
Requires-Dist: boto3 (==1.12.10)
Requires-Dist: botocore (==1.15.21)
Requires-Dist: kubernetes (==12.0.1)
Requires-Dist: wheel (==0.36.2)
Requires-Dist: termcolor (~=1.1.0)
Requires-Dist: docker-pycreds (==0.4.0)
Requires-Dist: typing (==3.7.4.1)
Requires-Dist: GitPython (==3.1.11)
Requires-Dist: moto (==1.3.14)
Requires-Dist: diskcache (==3.1.1)
Requires-Dist: croniter (==0.3.31)
Requires-Dist: pytz (==2020.5)
Requires-Dist: pytzdata (==2020.1)
Requires-Dist: freezegun (==1.1.0)
Requires-Dist: statsd (<4.0,>=3.3.0)
Requires-Dist: sqlalchemy (~=1.3.15)
Requires-Dist: flatdict (==3.4.0)
Requires-Dist: jinja2 (<2.11.0,>=2.10.1)
Requires-Dist: python-json-logger (==2.0.1)
